{
  "timestamp": "2025-01-18 01:45:24",
  "total": 108,
  "topics": [
    {
      "rank": "1",
      "title": "发展冰雪产业丰富群众冰雪赛事活动",
      "link": "https://s.weibo.com/weibo?q=%E5%8F%91%E5%B1%95%E5%86%B0%E9%9B%AA%E4%BA%A7%E4%B8%9A%E4%B8%B0%E5%AF%8C%E7%BE%A4%E4%BC%97%E5%86%B0%E9%9B%AA%E8%B5%9B%E4%BA%8B%E6%B4%BB%E5%8A%A8",
      "hot": "",
      "platform": "微博",
      "crawlTime": "2025-01-18 01:45:24"
    },
    {
      "rank": "2",
      "title": "宋祖儿方称寻人男子是寄宿家庭弟弟",
      "link": "https://s.weibo.com/weibo?q=%E5%AE%8B%E7%A5%96%E5%84%BF%E6%96%B9%E7%A7%B0%E5%AF%BB%E4%BA%BA%E7%94%B7%E5%AD%90%E6%98%AF%E5%AF%84%E5%AE%BF%E5%AE%B6%E5%BA%AD%E5%BC%9F%E5%BC%9F",
      "hot": {
        "value": "114.4万"
      },
      "platform": "微博",
      "crawlTime": "2025-01-18 01:45:24"
    },
    {
      "rank": "3",
      "title": "周受资称特朗普致力于与其公司合作",
      "link": "https://s.weibo.com/weibo?q=%E5%91%A8%E5%8F%97%E8%B5%84%E7%A7%B0%E7%89%B9%E6%9C%97%E6%99%AE%E8%87%B4%E5%8A%9B%E4%BA%8E%E4%B8%8E%E5%85%B6%E5%85%AC%E5%8F%B8%E5%90%88%E4%BD%9C",
      "hot": {
        "value": "75.1万"
      },
      "platform": "微博",
      "crawlTime": "2025-01-18 01:45:24"
    },
    {
      "rank": "4",
      "title": "我国找矿又有重大突破",
      "link": "https://s.weibo.com/weibo?q=%E6%88%91%E5%9B%BD%E6%89%BE%E7%9F%BF%E5%8F%88%E6%9C%89%E9%87%8D%E5%A4%A7%E7%AA%81%E7%A0%B4",
      "hot": {
        "value": "62.1万"
      },
      "platform": "微博",
      "crawlTime": "2025-01-18 01:45:24"
    },
    {
      "rank": "5",
      "title": "Apple新春歌舞片幕后",
      "link": "https://s.weibo.com/weibo?q=Apple%E6%96%B0%E6%98%A5%E6%AD%8C%E8%88%9E%E7%89%87%E5%B9%95%E5%90%8E",
      "hot": "",
      "platform": "微博",
      "crawlTime": "2025-01-18 01:45:24"
    },
    {
      "rank": "6",
      "title": "中美网友对账后有些人天塌了",
      "link": "https://s.weibo.com/weibo?q=%E4%B8%AD%E7%BE%8E%E7%BD%91%E5%8F%8B%E5%AF%B9%E8%B4%A6%E5%90%8E%E6%9C%89%E4%BA%9B%E4%BA%BA%E5%A4%A9%E5%A1%8C%E4%BA%86",
      "hot": {
        "value": "56.6万"
      },
      "platform": "微博",
      "crawlTime": "2025-01-18 01:45:24"
    },
    {
      "rank": "7",
      "title": "强闪光灯下的李昀锐",
      "link": "https://s.weibo.com/weibo?q=%E5%BC%BA%E9%97%AA%E5%85%89%E7%81%AF%E4%B8%8B%E7%9A%84%E6%9D%8E%E6%98%80%E9%94%90",
      "hot": {
        "category": "盛典",
        "value": "436322"
      },
      "platform": "微博",
      "crawlTime": "2025-01-18 01:45:24"
    },
    {
      "rank": "8",
      "title": "中美网友在小红书上热聊",
      "link": "https://s.weibo.com/weibo?q=%E4%B8%AD%E7%BE%8E%E7%BD%91%E5%8F%8B%E5%9C%A8%E5%B0%8F%E7%BA%A2%E4%B9%A6%E4%B8%8A%E7%83%AD%E8%81%8A",
      "hot": {
        "value": "42.2万"
      },
      "platform": "微博",
      "crawlTime": "2025-01-18 01:45:24"
    },
    {
      "rank": "9",
      "title": "锦囊妙录全员直播献妙计",
      "link": "https://s.weibo.com/weibo?q=%E9%94%A6%E5%9B%8A%E5%A6%99%E5%BD%95%E5%85%A8%E5%91%98%E7%9B%B4%E6%92%AD%E7%8C%AE%E5%A6%99%E8%AE%A1",
      "hot": "",
      "platform": "微博",
      "crawlTime": "2025-01-18 01:45:24"
    },
    {
      "rank": "10",
      "title": "李现回复湖南卫视",
      "link": "https://s.weibo.com/weibo?q=%E6%9D%8E%E7%8E%B0%E5%9B%9E%E5%A4%8D%E6%B9%96%E5%8D%97%E5%8D%AB%E8%A7%86",
      "hot": {
        "category": "剧集",
        "value": "402730"
      },
      "platform": "微博",
      "crawlTime": "2025-01-18 01:45:24"
    },
    {
      "rank": "11",
      "title": "妈这就是你儿子搞的世界级大工程",
      "link": "https://s.weibo.com/weibo?q=%E5%A6%88%E8%BF%99%E5%B0%B1%E6%98%AF%E4%BD%A0%E5%84%BF%E5%AD%90%E6%90%9E%E7%9A%84%E4%B8%96%E7%95%8C%E7%BA%A7%E5%A4%A7%E5%B7%A5%E7%A8%8B",
      "hot": {
        "value": "34.6万"
      },
      "platform": "微博",
      "crawlTime": "2025-01-18 01:45:24"
    },
    {
      "rank": "12",
      "title": "本科毕业入伍不到1年立一等功",
      "link": "https://s.weibo.com/weibo?q=%E6%9C%AC%E7%A7%91%E6%AF%95%E4%B8%9A%E5%85%A5%E4%BC%8D%E4%B8%8D%E5%88%B01%E5%B9%B4%E7%AB%8B%E4%B8%80%E7%AD%89%E5%8A%9F",
      "hot": {
        "value": "31.3万"
      },
      "platform": "微博",
      "crawlTime": "2025-01-18 01:45:24"
    },
    {
      "rank": "13",
      "title": "布林肯记者会上记者被抬走",
      "link": "https://s.weibo.com/weibo?q=%E5%B8%83%E6%9E%97%E8%82%AF%E8%AE%B0%E8%80%85%E4%BC%9A%E4%B8%8A%E8%AE%B0%E8%80%85%E8%A2%AB%E6%8A%AC%E8%B5%B0",
      "hot": {
        "value": "31.1万"
      },
      "platform": "微博",
      "crawlTime": "2025-01-18 01:45:24"
    },
    {
      "rank": "14",
      "title": "韩国第一夫人暴瘦白发",
      "link": "https://s.weibo.com/weibo?q=%E9%9F%A9%E5%9B%BD%E7%AC%AC%E4%B8%80%E5%A4%AB%E4%BA%BA%E6%9A%B4%E7%98%A6%E7%99%BD%E5%8F%91",
      "hot": {
        "value": "31.0万"
      },
      "platform": "微博",
      "crawlTime": "2025-01-18 01:45:24"
    },
    {
      "rank": "15",
      "title": "美最高法支持政府对TikTok强迫出售令",
      "link": "https://s.weibo.com/weibo?q=%E7%BE%8E%E6%9C%80%E9%AB%98%E6%B3%95%E6%94%AF%E6%8C%81%E6%94%BF%E5%BA%9C%E5%AF%B9TikTok%E5%BC%BA%E8%BF%AB%E5%87%BA%E5%94%AE%E4%BB%A4",
      "hot": {
        "value": "31.0万"
      },
      "platform": "微博",
      "crawlTime": "2025-01-18 01:45:24"
    },
    {
      "rank": "16",
      "title": "洪尚秀妻子回应金敏喜怀孕",
      "link": "https://s.weibo.com/weibo?q=%E6%B4%AA%E5%B0%9A%E7%A7%80%E5%A6%BB%E5%AD%90%E5%9B%9E%E5%BA%94%E9%87%91%E6%95%8F%E5%96%9C%E6%80%80%E5%AD%95",
      "hot": {
        "value": "31.0万"
      },
      "platform": "微博",
      "crawlTime": "2025-01-18 01:45:24"
    },
    {
      "rank": "17",
      "title": "2025春晚4个分会场首次合排",
      "link": "https://s.weibo.com/weibo?q=2025%E6%98%A5%E6%99%9A4%E4%B8%AA%E5%88%86%E4%BC%9A%E5%9C%BA%E9%A6%96%E6%AC%A1%E5%90%88%E6%8E%92",
      "hot": {
        "category": "晚会",
        "value": "273567"
      },
      "platform": "微博",
      "crawlTime": "2025-01-18 01:45:24"
    },
    {
      "rank": "18",
      "title": "10岁男孩被批评报警举报父亲藏罂粟壳",
      "link": "https://s.weibo.com/weibo?q=10%E5%B2%81%E7%94%B7%E5%AD%A9%E8%A2%AB%E6%89%B9%E8%AF%84%E6%8A%A5%E8%AD%A6%E4%B8%BE%E6%8A%A5%E7%88%B6%E4%BA%B2%E8%97%8F%E7%BD%82%E7%B2%9F%E5%A3%B3",
      "hot": {
        "value": "26.2万"
      },
      "platform": "微博",
      "crawlTime": "2025-01-18 01:45:24"
    },
    {
      "rank": "19",
      "title": "男子日本出差意外发现日军罪证",
      "link": "https://s.weibo.com/weibo?q=%E7%94%B7%E5%AD%90%E6%97%A5%E6%9C%AC%E5%87%BA%E5%B7%AE%E6%84%8F%E5%A4%96%E5%8F%91%E7%8E%B0%E6%97%A5%E5%86%9B%E7%BD%AA%E8%AF%81",
      "hot": {
        "value": "23.7万"
      },
      "platform": "微博",
      "crawlTime": "2025-01-18 01:45:24"
    },
    {
      "rank": "20",
      "title": "成都一火锅店员工在后厨小便属实",
      "link": "https://s.weibo.com/weibo?q=%E6%88%90%E9%83%BD%E4%B8%80%E7%81%AB%E9%94%85%E5%BA%97%E5%91%98%E5%B7%A5%E5%9C%A8%E5%90%8E%E5%8E%A8%E5%B0%8F%E4%BE%BF%E5%B1%9E%E5%AE%9E",
      "hot": {
        "value": "21.4万"
      },
      "platform": "微博",
      "crawlTime": "2025-01-18 01:45:24"
    },
    {
      "rank": "21",
      "title": "BC创始人展示李昀锐的照片",
      "link": "https://s.weibo.com/weibo?q=BC%E5%88%9B%E5%A7%8B%E4%BA%BA%E5%B1%95%E7%A4%BA%E6%9D%8E%E6%98%80%E9%94%90%E7%9A%84%E7%85%A7%E7%89%87",
      "hot": {
        "category": "盛典",
        "value": "167615"
      },
      "platform": "微博",
      "crawlTime": "2025-01-18 01:45:24"
    },
    {
      "rank": "22",
      "title": "美国针对TikTok与华为的是一批人",
      "link": "https://s.weibo.com/weibo?q=%E7%BE%8E%E5%9B%BD%E9%92%88%E5%AF%B9TikTok%E4%B8%8E%E5%8D%8E%E4%B8%BA%E7%9A%84%E6%98%AF%E4%B8%80%E6%89%B9%E4%BA%BA",
      "hot": {
        "value": "16.7万"
      },
      "platform": "微博",
      "crawlTime": "2025-01-18 01:45:24"
    },
    {
      "rank": "23",
      "title": "何惟芳被贬为官奴",
      "link": "https://s.weibo.com/weibo?q=%E4%BD%95%E6%83%9F%E8%8A%B3%E8%A2%AB%E8%B4%AC%E4%B8%BA%E5%AE%98%E5%A5%B4",
      "hot": {
        "category": "剧集",
        "value": "164627"
      },
      "platform": "微博",
      "crawlTime": "2025-01-18 01:45:24"
    },
    {
      "rank": "24",
      "title": "刘谦抗癌康复后将登春晚",
      "link": "https://s.weibo.com/weibo?q=%E5%88%98%E8%B0%A6%E6%8A%97%E7%99%8C%E5%BA%B7%E5%A4%8D%E5%90%8E%E5%B0%86%E7%99%BB%E6%98%A5%E6%99%9A",
      "hot": {
        "category": "晚会",
        "value": "164003"
      },
      "platform": "微博",
      "crawlTime": "2025-01-18 01:45:24"
    },
    {
      "rank": "25",
      "title": "90后一家三口一年消费20万",
      "link": "https://s.weibo.com/weibo?q=90%E5%90%8E%E4%B8%80%E5%AE%B6%E4%B8%89%E5%8F%A3%E4%B8%80%E5%B9%B4%E6%B6%88%E8%B4%B920%E4%B8%87",
      "hot": {
        "value": "16.3万"
      },
      "platform": "微博",
      "crawlTime": "2025-01-18 01:45:24"
    },
    {
      "rank": "26",
      "title": "狗妈妈凌晨守在摊前作揖乞食",
      "link": "https://s.weibo.com/weibo?q=%E7%8B%97%E5%A6%88%E5%A6%88%E5%87%8C%E6%99%A8%E5%AE%88%E5%9C%A8%E6%91%8A%E5%89%8D%E4%BD%9C%E6%8F%96%E4%B9%9E%E9%A3%9F",
      "hot": {
        "value": "16.1万"
      },
      "platform": "微博",
      "crawlTime": "2025-01-18 01:45:24"
    },
    {
      "rank": "27",
      "title": "看似养胃实则伤胃的4个习惯",
      "link": "https://s.weibo.com/weibo?q=%E7%9C%8B%E4%BC%BC%E5%85%BB%E8%83%83%E5%AE%9E%E5%88%99%E4%BC%A4%E8%83%83%E7%9A%844%E4%B8%AA%E4%B9%A0%E6%83%AF",
      "hot": {
        "value": "16.0万"
      },
      "platform": "微博",
      "crawlTime": "2025-01-18 01:45:24"
    },
    {
      "rank": "28",
      "title": "佛山电翰说不想再消耗工人身份",
      "link": "https://s.weibo.com/weibo?q=%E4%BD%9B%E5%B1%B1%E7%94%B5%E7%BF%B0%E8%AF%B4%E4%B8%8D%E6%83%B3%E5%86%8D%E6%B6%88%E8%80%97%E5%B7%A5%E4%BA%BA%E8%BA%AB%E4%BB%BD",
      "hot": {
        "value": "15.9万"
      },
      "platform": "微博",
      "crawlTime": "2025-01-18 01:45:24"
    },
    {
      "rank": "29",
      "title": "光与夜之恋",
      "link": "https://s.weibo.com/weibo?q=%E5%85%89%E4%B8%8E%E5%A4%9C%E4%B9%8B%E6%81%8B",
      "hot": {
        "value": "15.6万"
      },
      "platform": "微博",
      "crawlTime": "2025-01-18 01:45:24"
    },
    {
      "rank": "30",
      "title": "网红李维刚就牛肉卷事件道歉",
      "link": "https://s.weibo.com/weibo?q=%E7%BD%91%E7%BA%A2%E6%9D%8E%E7%BB%B4%E5%88%9A%E5%B0%B1%E7%89%9B%E8%82%89%E5%8D%B7%E4%BA%8B%E4%BB%B6%E9%81%93%E6%AD%89",
      "hot": {
        "value": "14.4万"
      },
      "platform": "微博",
      "crawlTime": "2025-01-18 01:45:24"
    },
    {
      "rank": "31",
      "title": "这么多人偏偏让他站了C位",
      "link": "https://s.weibo.com/weibo?q=%E8%BF%99%E4%B9%88%E5%A4%9A%E4%BA%BA%E5%81%8F%E5%81%8F%E8%AE%A9%E4%BB%96%E7%AB%99%E4%BA%86C%E4%BD%8D",
      "hot": {
        "value": "14.4万"
      },
      "platform": "微博",
      "crawlTime": "2025-01-18 01:45:24"
    },
    {
      "rank": "32",
      "title": "李维刚承认带货原切牛肉卷为合成肉",
      "link": "https://s.weibo.com/weibo?q=%E6%9D%8E%E7%BB%B4%E5%88%9A%E6%89%BF%E8%AE%A4%E5%B8%A6%E8%B4%A7%E5%8E%9F%E5%88%87%E7%89%9B%E8%82%89%E5%8D%B7%E4%B8%BA%E5%90%88%E6%88%90%E8%82%89",
      "hot": {
        "value": "13.9万"
      },
      "platform": "微博",
      "crawlTime": "2025-01-18 01:45:24"
    },
    {
      "rank": "33",
      "title": "周受资称将确保TikTok继续繁荣",
      "link": "https://s.weibo.com/weibo?q=%E5%91%A8%E5%8F%97%E8%B5%84%E7%A7%B0%E5%B0%86%E7%A1%AE%E4%BF%9DTikTok%E7%BB%A7%E7%BB%AD%E7%B9%81%E8%8D%A3",
      "hot": {
        "value": "13.3万"
      },
      "platform": "微博",
      "crawlTime": "2025-01-18 01:45:24"
    },
    {
      "rank": "34",
      "title": "在上海花2000买一个黑天鹅生日蛋糕",
      "link": "https://s.weibo.com/weibo?q=%E5%9C%A8%E4%B8%8A%E6%B5%B7%E8%8A%B12000%E4%B9%B0%E4%B8%80%E4%B8%AA%E9%BB%91%E5%A4%A9%E9%B9%85%E7%94%9F%E6%97%A5%E8%9B%8B%E7%B3%95",
      "hot": {
        "value": "13.3万"
      },
      "platform": "微博",
      "crawlTime": "2025-01-18 01:45:24"
    },
    {
      "rank": "35",
      "title": "黄圣依有多讨厌直播",
      "link": "https://s.weibo.com/weibo?q=%E9%BB%84%E5%9C%A3%E4%BE%9D%E6%9C%89%E5%A4%9A%E8%AE%A8%E5%8E%8C%E7%9B%B4%E6%92%AD",
      "hot": {
        "value": "13.2万"
      },
      "platform": "微博",
      "crawlTime": "2025-01-18 01:45:24"
    },
    {
      "rank": "36",
      "title": "王鹤棣这个镜头一眼万年",
      "link": "https://s.weibo.com/weibo?q=%E7%8E%8B%E9%B9%A4%E6%A3%A3%E8%BF%99%E4%B8%AA%E9%95%9C%E5%A4%B4%E4%B8%80%E7%9C%BC%E4%B8%87%E5%B9%B4",
      "hot": {
        "category": "剧集",
        "value": "131726"
      },
      "platform": "微博",
      "crawlTime": "2025-01-18 01:45:24"
    },
    {
      "rank": "37",
      "title": "白鹿晒白烁好多小挂坠",
      "link": "https://s.weibo.com/weibo?q=%E7%99%BD%E9%B9%BF%E6%99%92%E7%99%BD%E7%83%81%E5%A5%BD%E5%A4%9A%E5%B0%8F%E6%8C%82%E5%9D%A0",
      "hot": {
        "category": "剧集",
        "value": "128795"
      },
      "platform": "微博",
      "crawlTime": "2025-01-18 01:45:24"
    },
    {
      "rank": "38",
      "title": "王一博亚冬会开幕式主题歌推广曲MV",
      "link": "https://s.weibo.com/weibo?q=%E7%8E%8B%E4%B8%80%E5%8D%9A%E4%BA%9A%E5%86%AC%E4%BC%9A%E5%BC%80%E5%B9%95%E5%BC%8F%E4%B8%BB%E9%A2%98%E6%AD%8C%E6%8E%A8%E5%B9%BF%E6%9B%B2MV",
      "hot": {
        "value": "12.2万"
      },
      "platform": "微博",
      "crawlTime": "2025-01-18 01:45:24"
    },
    {
      "rank": "39",
      "title": "官方通报火锅店员工在后厨小便",
      "link": "https://s.weibo.com/weibo?q=%E5%AE%98%E6%96%B9%E9%80%9A%E6%8A%A5%E7%81%AB%E9%94%85%E5%BA%97%E5%91%98%E5%B7%A5%E5%9C%A8%E5%90%8E%E5%8E%A8%E5%B0%8F%E4%BE%BF",
      "hot": {
        "value": "11.8万"
      },
      "platform": "微博",
      "crawlTime": "2025-01-18 01:45:24"
    },
    {
      "rank": "40",
      "title": "徐志胜周一围朱丹这两口子太吓人了",
      "link": "https://s.weibo.com/weibo?q=%E5%BE%90%E5%BF%97%E8%83%9C%E5%91%A8%E4%B8%80%E5%9B%B4%E6%9C%B1%E4%B8%B9%E8%BF%99%E4%B8%A4%E5%8F%A3%E5%AD%90%E5%A4%AA%E5%90%93%E4%BA%BA%E4%BA%86",
      "hot": {
        "value": "11.5万"
      },
      "platform": "微博",
      "crawlTime": "2025-01-18 01:45:24"
    },
    {
      "rank": "41",
      "title": "泰总理用中文向游客保证安全",
      "link": "https://s.weibo.com/weibo?q=%E6%B3%B0%E6%80%BB%E7%90%86%E7%94%A8%E4%B8%AD%E6%96%87%E5%90%91%E6%B8%B8%E5%AE%A2%E4%BF%9D%E8%AF%81%E5%AE%89%E5%85%A8",
      "hot": {
        "value": "10.5万"
      },
      "platform": "微博",
      "crawlTime": "2025-01-18 01:45:24"
    },
    {
      "rank": "42",
      "title": "光与夜之恋先锋定格",
      "link": "https://s.weibo.com/weibo?q=%E5%85%89%E4%B8%8E%E5%A4%9C%E4%B9%8B%E6%81%8B%E5%85%88%E9%94%8B%E5%AE%9A%E6%A0%BC",
      "hot": {
        "value": "10.5万"
      },
      "platform": "微博",
      "crawlTime": "2025-01-18 01:45:24"
    },
    {
      "rank": "43",
      "title": "谷爱凌时隔5年再夺世界杯冠军",
      "link": "https://s.weibo.com/weibo?q=%E8%B0%B7%E7%88%B1%E5%87%8C%E6%97%B6%E9%9A%945%E5%B9%B4%E5%86%8D%E5%A4%BA%E4%B8%96%E7%95%8C%E6%9D%AF%E5%86%A0%E5%86%9B",
      "hot": {
        "value": "9.8万"
      },
      "platform": "微博",
      "crawlTime": "2025-01-18 01:45:24"
    },
    {
      "rank": "44",
      "title": "庞博新综艺被气到背对镜头",
      "link": "https://s.weibo.com/weibo?q=%E5%BA%9E%E5%8D%9A%E6%96%B0%E7%BB%BC%E8%89%BA%E8%A2%AB%E6%B0%94%E5%88%B0%E8%83%8C%E5%AF%B9%E9%95%9C%E5%A4%B4",
      "hot": {
        "value": "9.5万"
      },
      "platform": "微博",
      "crawlTime": "2025-01-18 01:45:24"
    },
    {
      "rank": "45",
      "title": "NSA控制我国上万网络设备窃取数据",
      "link": "https://s.weibo.com/weibo?q=NSA%E6%8E%A7%E5%88%B6%E6%88%91%E5%9B%BD%E4%B8%8A%E4%B8%87%E7%BD%91%E7%BB%9C%E8%AE%BE%E5%A4%87%E7%AA%83%E5%8F%96%E6%95%B0%E6%8D%AE",
      "hot": {
        "value": "9.1万"
      },
      "platform": "微博",
      "crawlTime": "2025-01-18 01:45:24"
    },
    {
      "rank": "46",
      "title": "91岁崔道植宣布警号022272重启",
      "link": "https://s.weibo.com/weibo?q=91%E5%B2%81%E5%B4%94%E9%81%93%E6%A4%8D%E5%AE%A3%E5%B8%83%E8%AD%A6%E5%8F%B7022272%E9%87%8D%E5%90%AF",
      "hot": {
        "value": "8.8万"
      },
      "platform": "微博",
      "crawlTime": "2025-01-18 01:45:24"
    },
    {
      "rank": "47",
      "title": "管晨辰因伤口钢板断掉再次手术",
      "link": "https://s.weibo.com/weibo?q=%E7%AE%A1%E6%99%A8%E8%BE%B0%E5%9B%A0%E4%BC%A4%E5%8F%A3%E9%92%A2%E6%9D%BF%E6%96%AD%E6%8E%89%E5%86%8D%E6%AC%A1%E6%89%8B%E6%9C%AF",
      "hot": {
        "value": "8.7万"
      },
      "platform": "微博",
      "crawlTime": "2025-01-18 01:45:24"
    },
    {
      "rank": "48",
      "title": "齐司礼新卡",
      "link": "https://s.weibo.com/weibo?q=%E9%BD%90%E5%8F%B8%E7%A4%BC%E6%96%B0%E5%8D%A1",
      "hot": {
        "value": "8.7万"
      },
      "platform": "微博",
      "crawlTime": "2025-01-18 01:45:24"
    },
    {
      "rank": "49",
      "title": "巴特勒复出",
      "link": "https://s.weibo.com/weibo?q=%E5%B7%B4%E7%89%B9%E5%8B%92%E5%A4%8D%E5%87%BA",
      "hot": {
        "value": "8.6万"
      },
      "platform": "微博",
      "crawlTime": "2025-01-18 01:45:24"
    },
    {
      "rank": "50",
      "title": "郑州动物王国的巴西貘火了",
      "link": "https://s.weibo.com/weibo?q=%E9%83%91%E5%B7%9E%E5%8A%A8%E7%89%A9%E7%8E%8B%E5%9B%BD%E7%9A%84%E5%B7%B4%E8%A5%BF%E8%B2%98%E7%81%AB%E4%BA%86",
      "hot": {
        "value": "8.6万"
      },
      "platform": "微博",
      "crawlTime": "2025-01-18 01:45:24"
    },
    {
      "rank": "51",
      "title": "台湾当归",
      "link": "https://s.weibo.com/weibo?q=%E5%8F%B0%E6%B9%BE%E5%BD%93%E5%BD%92",
      "hot": {
        "value": "8.1万"
      },
      "platform": "微博",
      "crawlTime": "2025-01-18 01:45:24"
    },
    {
      "rank": "52",
      "title": "特朗普多次公开支持TikTok",
      "link": "https://s.weibo.com/weibo?q=%E7%89%B9%E6%9C%97%E6%99%AE%E5%A4%9A%E6%AC%A1%E5%85%AC%E5%BC%80%E6%94%AF%E6%8C%81TikTok",
      "hot": {
        "value": "8.0万"
      },
      "platform": "微博",
      "crawlTime": "2025-01-18 01:45:24"
    },
    {
      "rank": "53",
      "title": "加沙停火1月19日生效",
      "link": "https://s.weibo.com/weibo?q=%E5%8A%A0%E6%B2%99%E5%81%9C%E7%81%AB1%E6%9C%8819%E6%97%A5%E7%94%9F%E6%95%88",
      "hot": {
        "value": "8.0万"
      },
      "platform": "微博",
      "crawlTime": "2025-01-18 01:45:24"
    },
    {
      "rank": "2025-01-18",
      "title": "双鱼座的进阶是从内耗到外耗",
      "link": "https://s.weibo.com/weibo?q=%E5%8F%8C%E9%B1%BC%E5%BA%A7%E7%9A%84%E8%BF%9B%E9%98%B6%E6%98%AF%E4%BB%8E%E5%86%85%E8%80%97%E5%88%B0%E5%A4%96%E8%80%97",
      "hot": {
        "value": "8.2万"
      },
      "platform": "微博",
      "crawlTime": "2025-01-18 01:45:24"
    },
    {
      "rank": "2025-01-18",
      "title": "香港100越野赛",
      "link": "https://s.weibo.com/weibo?q=%E9%A6%99%E6%B8%AF100%E8%B6%8A%E9%87%8E%E8%B5%9B",
      "hot": "",
      "platform": "微博",
      "crawlTime": "2025-01-18 01:45:24"
    },
    {
      "rank": "2025-01-18",
      "title": "边伯贤羊毛卷",
      "link": "https://s.weibo.com/weibo?q=%E8%BE%B9%E4%BC%AF%E8%B4%A4%E7%BE%8A%E6%AF%9B%E5%8D%B7",
      "hot": {
        "value": "8.4万"
      },
      "platform": "微博",
      "crawlTime": "2025-01-18 01:45:24"
    },
    {
      "rank": "2025-01-18",
      "title": "在新疆体验提前退休躺平",
      "link": "https://s.weibo.com/weibo?q=%E5%9C%A8%E6%96%B0%E7%96%86%E4%BD%93%E9%AA%8C%E6%8F%90%E5%89%8D%E9%80%80%E4%BC%91%E8%BA%BA%E5%B9%B3",
      "hot": {
        "value": "6.4万"
      },
      "platform": "微博",
      "crawlTime": "2025-01-18 01:45:24"
    },
    {
      "rank": "2025-01-18",
      "title": "再就业男团央视蛇年春晚第三次联排",
      "link": "https://s.weibo.com/weibo?q=%E5%86%8D%E5%B0%B1%E4%B8%9A%E7%94%B7%E5%9B%A2%E5%A4%AE%E8%A7%86%E8%9B%87%E5%B9%B4%E6%98%A5%E6%99%9A%E7%AC%AC%E4%B8%89%E6%AC%A1%E8%81%94%E6%8E%92",
      "hot": {
        "category": "晚会",
        "value": "85062"
      },
      "platform": "微博",
      "crawlTime": "2025-01-18 01:45:24"
    },
    {
      "rank": "2025-01-18",
      "title": "官方晒青奥会明星樊振东在列",
      "link": "https://s.weibo.com/weibo?q=%E5%AE%98%E6%96%B9%E6%99%92%E9%9D%92%E5%A5%A5%E4%BC%9A%E6%98%8E%E6%98%9F%E6%A8%8A%E6%8C%AF%E4%B8%9C%E5%9C%A8%E5%88%97",
      "hot": {
        "value": "18.6万"
      },
      "platform": "微博",
      "crawlTime": "2025-01-18 01:45:24"
    },
    {
      "rank": "2025-01-18",
      "title": "金铲铲2025天选福星",
      "link": "https://s.weibo.com/weibo?q=%E9%87%91%E9%93%B2%E9%93%B22025%E5%A4%A9%E9%80%89%E7%A6%8F%E6%98%9F",
      "hot": "",
      "platform": "微博",
      "crawlTime": "2025-01-18 01:45:24"
    },
    {
      "rank": "2025-01-18",
      "title": "让心情瞬间变好的4个地方",
      "link": "https://s.weibo.com/weibo?q=%E8%AE%A9%E5%BF%83%E6%83%85%E7%9E%AC%E9%97%B4%E5%8F%98%E5%A5%BD%E7%9A%844%E4%B8%AA%E5%9C%B0%E6%96%B9",
      "hot": {
        "value": "6.4万"
      },
      "platform": "微博",
      "crawlTime": "2025-01-18 01:45:24"
    },
    {
      "rank": "2025-01-18",
      "title": "SK发文道歉",
      "link": "https://s.weibo.com/weibo?q=SK%E5%8F%91%E6%96%87%E9%81%93%E6%AD%89",
      "hot": {
        "value": "7.8万"
      },
      "platform": "微博",
      "crawlTime": "2025-01-18 01:45:24"
    },
    {
      "rank": "2025-01-18",
      "title": "肖战徐克精益求精",
      "link": "https://s.weibo.com/weibo?q=%E8%82%96%E6%88%98%E5%BE%90%E5%85%8B%E7%B2%BE%E7%9B%8A%E6%B1%82%E7%B2%BE",
      "hot": {
        "category": "电影",
        "value": "68476"
      },
      "platform": "微博",
      "crawlTime": "2025-01-18 01:45:24"
    },
    {
      "rank": "2025-01-18",
      "title": "领克EM-P春运搭子",
      "link": "https://s.weibo.com/weibo?q=%E9%A2%86%E5%85%8BEM-P%E6%98%A5%E8%BF%90%E6%90%AD%E5%AD%90",
      "hot": "",
      "platform": "微博",
      "crawlTime": "2025-01-18 01:45:24"
    },
    {
      "rank": "2025-01-18",
      "title": "王俊凯祝最最帅的杰伦哥生日快乐",
      "link": "https://s.weibo.com/weibo?q=%E7%8E%8B%E4%BF%8A%E5%87%AF%E7%A5%9D%E6%9C%80%E6%9C%80%E5%B8%85%E7%9A%84%E6%9D%B0%E4%BC%A6%E5%93%A5%E7%94%9F%E6%97%A5%E5%BF%AB%E4%B9%90",
      "hot": {
        "value": "8.2万"
      },
      "platform": "微博",
      "crawlTime": "2025-01-18 01:45:24"
    },
    {
      "rank": "2025-01-18",
      "title": "奖状之大一个书包放不下",
      "link": "https://s.weibo.com/weibo?q=%E5%A5%96%E7%8A%B6%E4%B9%8B%E5%A4%A7%E4%B8%80%E4%B8%AA%E4%B9%A6%E5%8C%85%E6%94%BE%E4%B8%8D%E4%B8%8B",
      "hot": {
        "value": "3.8万"
      },
      "platform": "微博",
      "crawlTime": "2025-01-18 01:45:24"
    },
    {
      "rank": "2025-01-18",
      "title": "恋与深空周年快乐",
      "link": "https://s.weibo.com/weibo?q=%E6%81%8B%E4%B8%8E%E6%B7%B1%E7%A9%BA%E5%91%A8%E5%B9%B4%E5%BF%AB%E4%B9%90",
      "hot": {
        "value": "6.6万"
      },
      "platform": "微博",
      "crawlTime": "2025-01-18 01:45:24"
    },
    {
      "rank": "2025-01-18",
      "title": "李现TO我最好的侍卫",
      "link": "https://s.weibo.com/weibo?q=%E6%9D%8E%E7%8E%B0TO%E6%88%91%E6%9C%80%E5%A5%BD%E7%9A%84%E4%BE%8D%E5%8D%AB",
      "hot": {
        "value": "6.4万"
      },
      "platform": "微博",
      "crawlTime": "2025-01-18 01:45:24"
    },
    {
      "rank": "2025-01-18",
      "title": "张雅钦把和杨紫的合照放C位",
      "link": "https://s.weibo.com/weibo?q=%E5%BC%A0%E9%9B%85%E9%92%A6%E6%8A%8A%E5%92%8C%E6%9D%A8%E7%B4%AB%E7%9A%84%E5%90%88%E7%85%A7%E6%94%BEC%E4%BD%8D",
      "hot": {
        "value": "7.2万"
      },
      "platform": "微博",
      "crawlTime": "2025-01-18 01:45:24"
    },
    {
      "rank": "2025-01-18",
      "title": "2025汽车以旧换新政策有啥变化",
      "link": "https://s.weibo.com/weibo?q=2025%E6%B1%BD%E8%BD%A6%E4%BB%A5%E6%97%A7%E6%8D%A2%E6%96%B0%E6%94%BF%E7%AD%96%E6%9C%89%E5%95%A5%E5%8F%98%E5%8C%96",
      "hot": {
        "category": "479.6万阅读",
        "value": "|"
      },
      "platform": "微博",
      "crawlTime": "2025-01-18 01:45:24"
    },
    {
      "rank": "2025-01-18",
      "title": "蔚县春节花样多",
      "link": "https://s.weibo.com/weibo?q=%E8%94%9A%E5%8E%BF%E6%98%A5%E8%8A%82%E8%8A%B1%E6%A0%B7%E5%A4%9A",
      "hot": {
        "category": "104.2万阅读",
        "value": "|"
      },
      "platform": "微博",
      "crawlTime": "2025-01-18 01:45:24"
    },
    {
      "rank": "2025-01-18",
      "title": "氢气球爆燃温度超400摄氏度",
      "link": "https://s.weibo.com/weibo?q=%E6%B0%A2%E6%B0%94%E7%90%83%E7%88%86%E7%87%83%E6%B8%A9%E5%BA%A6%E8%B6%85400%E6%91%84%E6%B0%8F%E5%BA%A6",
      "hot": {
        "category": "252.6万阅读",
        "value": "|"
      },
      "platform": "微博",
      "crawlTime": "2025-01-18 01:45:24"
    },
    {
      "rank": "2025-01-18",
      "title": "氢气球遇静电瞬间爆燃",
      "link": "https://s.weibo.com/weibo?q=%E6%B0%A2%E6%B0%94%E7%90%83%E9%81%87%E9%9D%99%E7%94%B5%E7%9E%AC%E9%97%B4%E7%88%86%E7%87%83",
      "hot": {
        "category": "237.5万阅读",
        "value": "|"
      },
      "platform": "微博",
      "crawlTime": "2025-01-18 01:45:24"
    },
    {
      "rank": "2025-01-18",
      "title": "档位调太大神器擦窗户时玻璃炸裂",
      "link": "https://s.weibo.com/weibo?q=%E6%A1%A3%E4%BD%8D%E8%B0%83%E5%A4%AA%E5%A4%A7%E7%A5%9E%E5%99%A8%E6%93%A6%E7%AA%97%E6%88%B7%E6%97%B6%E7%8E%BB%E7%92%83%E7%82%B8%E8%A3%82",
      "hot": {
        "category": "237.7万阅读",
        "value": "|"
      },
      "platform": "微博",
      "crawlTime": "2025-01-18 01:45:24"
    },
    {
      "rank": "2025-01-18",
      "title": "李华以后别写信了评论区见吧",
      "link": "https://s.weibo.com/weibo?q=%E6%9D%8E%E5%8D%8E%E4%BB%A5%E5%90%8E%E5%88%AB%E5%86%99%E4%BF%A1%E4%BA%86%E8%AF%84%E8%AE%BA%E5%8C%BA%E8%A7%81%E5%90%A7",
      "hot": {
        "category": "517.3万阅读",
        "value": "|"
      },
      "platform": "微博",
      "crawlTime": "2025-01-18 01:45:24"
    },
    {
      "rank": "2025-01-18",
      "title": "家国同春 四海共享",
      "link": "https://s.weibo.com/weibo?q=%E5%AE%B6%E5%9B%BD%E5%90%8C%E6%98%A5+%E5%9B%9B%E6%B5%B7%E5%85%B1%E4%BA%AB",
      "hot": "",
      "platform": "微博",
      "crawlTime": "2025-01-18 01:45:24"
    },
    {
      "rank": "2025-01-18",
      "title": "美国网友花式亮招和中国人唠嗑",
      "link": "https://s.weibo.com/weibo?q=%E7%BE%8E%E5%9B%BD%E7%BD%91%E5%8F%8B%E8%8A%B1%E5%BC%8F%E4%BA%AE%E6%8B%9B%E5%92%8C%E4%B8%AD%E5%9B%BD%E4%BA%BA%E5%94%A0%E5%97%91",
      "hot": {
        "category": "510.9万阅读",
        "value": "|"
      },
      "platform": "微博",
      "crawlTime": "2025-01-18 01:45:24"
    },
    {
      "rank": "2025-01-18",
      "title": "刘宇宁央视新闻励志暖心曲",
      "link": "https://s.weibo.com/weibo?q=%E5%88%98%E5%AE%87%E5%AE%81%E5%A4%AE%E8%A7%86%E6%96%B0%E9%97%BB%E5%8A%B1%E5%BF%97%E6%9A%96%E5%BF%83%E6%9B%B2",
      "hot": {
        "category": "音乐",
        "value": "15476"
      },
      "platform": "微博",
      "crawlTime": "2025-01-18 01:45:24"
    },
    {
      "rank": "2025-01-18",
      "title": "73岁奶奶3元理发20多年不涨价",
      "link": "https://s.weibo.com/weibo?q=73%E5%B2%81%E5%A5%B6%E5%A5%B63%E5%85%83%E7%90%86%E5%8F%9120%E5%A4%9A%E5%B9%B4%E4%B8%8D%E6%B6%A8%E4%BB%B7",
      "hot": {
        "value": "2.4万"
      },
      "platform": "微博",
      "crawlTime": "2025-01-18 01:45:24"
    },
    {
      "rank": "2025-01-18",
      "title": "顾客多付2元钱老奶奶追着退回",
      "link": "https://s.weibo.com/weibo?q=%E9%A1%BE%E5%AE%A2%E5%A4%9A%E4%BB%982%E5%85%83%E9%92%B1%E8%80%81%E5%A5%B6%E5%A5%B6%E8%BF%BD%E7%9D%80%E9%80%80%E5%9B%9E",
      "hot": {
        "category": "405.1万阅读",
        "value": "|"
      },
      "platform": "微博",
      "crawlTime": "2025-01-18 01:45:24"
    },
    {
      "rank": "2025-01-18",
      "title": "长征二号丁运载火箭成功发射3颗卫星",
      "link": "https://s.weibo.com/weibo?q=%E9%95%BF%E5%BE%81%E4%BA%8C%E5%8F%B7%E4%B8%81%E8%BF%90%E8%BD%BD%E7%81%AB%E7%AE%AD%E6%88%90%E5%8A%9F%E5%8F%91%E5%B0%843%E9%A2%97%E5%8D%AB%E6%98%9F",
      "hot": {
        "category": "78.6万阅读",
        "value": "|"
      },
      "platform": "微博",
      "crawlTime": "2025-01-18 01:45:24"
    },
    {
      "rank": "2025-01-18",
      "title": "一路繁花芭莎大片",
      "link": "https://s.weibo.com/weibo?q=%E4%B8%80%E8%B7%AF%E7%B9%81%E8%8A%B1%E8%8A%AD%E8%8E%8E%E5%A4%A7%E7%89%87",
      "hot": {
        "category": "综艺",
        "value": "17271"
      },
      "platform": "微博",
      "crawlTime": "2025-01-18 01:45:24"
    },
    {
      "rank": "2025-01-18",
      "title": "26岁小伙参与建设横竖都第一的大桥",
      "link": "https://s.weibo.com/weibo?q=26%E5%B2%81%E5%B0%8F%E4%BC%99%E5%8F%82%E4%B8%8E%E5%BB%BA%E8%AE%BE%E6%A8%AA%E7%AB%96%E9%83%BD%E7%AC%AC%E4%B8%80%E7%9A%84%E5%A4%A7%E6%A1%A5",
      "hot": {
        "category": "1246.4万阅读",
        "value": "|"
      },
      "platform": "微博",
      "crawlTime": "2025-01-18 01:45:24"
    },
    {
      "rank": "2025-01-18",
      "title": "过年搭子选伊利",
      "link": "https://s.weibo.com/weibo?q=%E8%BF%87%E5%B9%B4%E6%90%AD%E5%AD%90%E9%80%89%E4%BC%8A%E5%88%A9",
      "hot": "",
      "platform": "微博",
      "crawlTime": "2025-01-18 01:45:24"
    },
    {
      "rank": "2025-01-18",
      "title": "中国的成绩属于每一位奋斗者",
      "link": "https://s.weibo.com/weibo?q=%E4%B8%AD%E5%9B%BD%E7%9A%84%E6%88%90%E7%BB%A9%E5%B1%9E%E4%BA%8E%E6%AF%8F%E4%B8%80%E4%BD%8D%E5%A5%8B%E6%96%97%E8%80%85",
      "hot": {
        "category": "184.3万阅读",
        "value": "|"
      },
      "platform": "微博",
      "crawlTime": "2025-01-18 01:45:24"
    },
    {
      "rank": "2025-01-18",
      "title": "国防新能源都需要的稀土矿上新",
      "link": "https://s.weibo.com/weibo?q=%E5%9B%BD%E9%98%B2%E6%96%B0%E8%83%BD%E6%BA%90%E9%83%BD%E9%9C%80%E8%A6%81%E7%9A%84%E7%A8%80%E5%9C%9F%E7%9F%BF%E4%B8%8A%E6%96%B0",
      "hot": {
        "category": "289.0万阅读",
        "value": "|"
      },
      "platform": "微博",
      "crawlTime": "2025-01-18 01:45:24"
    },
    {
      "rank": "2025-01-18",
      "title": "剃掉班味更有年味",
      "link": "https://s.weibo.com/weibo?q=%E5%89%83%E6%8E%89%E7%8F%AD%E5%91%B3%E6%9B%B4%E6%9C%89%E5%B9%B4%E5%91%B3",
      "hot": "",
      "platform": "微博",
      "crawlTime": "2025-01-18 01:45:24"
    },
    {
      "rank": "2025-01-18",
      "title": "封神第二部西岐阵营见面会",
      "link": "https://s.weibo.com/weibo?q=%E5%B0%81%E7%A5%9E%E7%AC%AC%E4%BA%8C%E9%83%A8%E8%A5%BF%E5%B2%90%E9%98%B5%E8%90%A5%E8%A7%81%E9%9D%A2%E4%BC%9A",
      "hot": {
        "category": "电影",
        "value": "24539"
      },
      "platform": "微博",
      "crawlTime": "2025-01-18 01:45:24"
    },
    {
      "rank": "2025-01-18",
      "title": "俄罗斯驻华大使馆发布消费提示",
      "link": "https://s.weibo.com/weibo?q=%E4%BF%84%E7%BD%97%E6%96%AF%E9%A9%BB%E5%8D%8E%E5%A4%A7%E4%BD%BF%E9%A6%86%E5%8F%91%E5%B8%83%E6%B6%88%E8%B4%B9%E6%8F%90%E7%A4%BA",
      "hot": {
        "category": "335.1万阅读",
        "value": "|"
      },
      "platform": "微博",
      "crawlTime": "2025-01-18 01:45:24"
    },
    {
      "rank": "2025-01-18",
      "title": "苏菲玛索说只靠脸长久不了",
      "link": "https://s.weibo.com/weibo?q=%E8%8B%8F%E8%8F%B2%E7%8E%9B%E7%B4%A2%E8%AF%B4%E5%8F%AA%E9%9D%A0%E8%84%B8%E9%95%BF%E4%B9%85%E4%B8%8D%E4%BA%86",
      "hot": {
        "value": "2.3万"
      },
      "platform": "微博",
      "crawlTime": "2025-01-18 01:45:24"
    },
    {
      "rank": "2025-01-18",
      "title": "200层楼高的空中走一条镂空的路",
      "link": "https://s.weibo.com/weibo?q=200%E5%B1%82%E6%A5%BC%E9%AB%98%E7%9A%84%E7%A9%BA%E4%B8%AD%E8%B5%B0%E4%B8%80%E6%9D%A1%E9%95%82%E7%A9%BA%E7%9A%84%E8%B7%AF",
      "hot": {
        "category": "568.3万阅读",
        "value": "|"
      },
      "platform": "微博",
      "crawlTime": "2025-01-18 01:45:24"
    },
    {
      "rank": "2025-01-18",
      "title": "2025狮子座好运清单",
      "link": "https://s.weibo.com/weibo?q=2025%E7%8B%AE%E5%AD%90%E5%BA%A7%E5%A5%BD%E8%BF%90%E6%B8%85%E5%8D%95",
      "hot": {
        "value": "4.5万"
      },
      "platform": "微博",
      "crawlTime": "2025-01-18 01:45:24"
    },
    {
      "rank": "2025-01-18",
      "title": "马斯克回应SpaceX星舰试飞后失联",
      "link": "https://s.weibo.com/weibo?q=%E9%A9%AC%E6%96%AF%E5%85%8B%E5%9B%9E%E5%BA%94SpaceX%E6%98%9F%E8%88%B0%E8%AF%95%E9%A3%9E%E5%90%8E%E5%A4%B1%E8%81%94",
      "hot": {
        "category": "1113.4万阅读",
        "value": "|"
      },
      "platform": "微博",
      "crawlTime": "2025-01-18 01:45:24"
    },
    {
      "rank": "2025-01-18",
      "title": "我的完美秘书",
      "link": "https://s.weibo.com/weibo?q=%E6%88%91%E7%9A%84%E5%AE%8C%E7%BE%8E%E7%A7%98%E4%B9%A6",
      "hot": {
        "value": "1.9万"
      },
      "platform": "微博",
      "crawlTime": "2025-01-18 01:45:24"
    },
    {
      "rank": "2025-01-18",
      "title": "埃文凯尔观看春晚第三次彩排",
      "link": "https://s.weibo.com/weibo?q=%E5%9F%83%E6%96%87%E5%87%AF%E5%B0%94%E8%A7%82%E7%9C%8B%E6%98%A5%E6%99%9A%E7%AC%AC%E4%B8%89%E6%AC%A1%E5%BD%A9%E6%8E%92",
      "hot": {
        "category": "综艺",
        "value": "57143"
      },
      "platform": "微博",
      "crawlTime": "2025-01-18 01:45:24"
    },
    {
      "rank": "2025-01-17",
      "title": "迪丽热巴红衣提灯拍摄路透",
      "link": "https://s.weibo.com/weibo?q=%E8%BF%AA%E4%B8%BD%E7%83%AD%E5%B7%B4%E7%BA%A2%E8%A1%A3%E6%8F%90%E7%81%AF%E6%8B%8D%E6%91%84%E8%B7%AF%E9%80%8F",
      "hot": {
        "category": "剧集",
        "value": "82545"
      },
      "platform": "微博",
      "crawlTime": "2025-01-18 01:45:24"
    },
    {
      "rank": "2025-01-17",
      "title": "希望美方务必慎重处理台湾问题",
      "link": "https://s.weibo.com/weibo?q=%E5%B8%8C%E6%9C%9B%E7%BE%8E%E6%96%B9%E5%8A%A1%E5%BF%85%E6%85%8E%E9%87%8D%E5%A4%84%E7%90%86%E5%8F%B0%E6%B9%BE%E9%97%AE%E9%A2%98",
      "hot": {
        "category": "2260.2万阅读",
        "value": "|"
      },
      "platform": "微博",
      "crawlTime": "2025-01-18 01:45:24"
    },
    {
      "rank": "2025-01-17",
      "title": "国乒称着眼洛杉矶奥运会梯队建设",
      "link": "https://s.weibo.com/weibo?q=%E5%9B%BD%E4%B9%92%E7%A7%B0%E7%9D%80%E7%9C%BC%E6%B4%9B%E6%9D%89%E7%9F%B6%E5%A5%A5%E8%BF%90%E4%BC%9A%E6%A2%AF%E9%98%9F%E5%BB%BA%E8%AE%BE",
      "hot": {
        "value": "7.2万"
      },
      "platform": "微博",
      "crawlTime": "2025-01-18 01:45:24"
    },
    {
      "rank": "2025-01-17",
      "title": "周深一边尖叫一边双杀",
      "link": "https://s.weibo.com/weibo?q=%E5%91%A8%E6%B7%B1%E4%B8%80%E8%BE%B9%E5%B0%96%E5%8F%AB%E4%B8%80%E8%BE%B9%E5%8F%8C%E6%9D%80",
      "hot": {
        "value": "3.7万"
      },
      "platform": "微博",
      "crawlTime": "2025-01-18 01:45:24"
    },
    {
      "rank": "2025-01-17",
      "title": "春节档你最想看哪部影片",
      "link": "https://s.weibo.com/weibo?q=%E6%98%A5%E8%8A%82%E6%A1%A3%E4%BD%A0%E6%9C%80%E6%83%B3%E7%9C%8B%E5%93%AA%E9%83%A8%E5%BD%B1%E7%89%87",
      "hot": {
        "category": "1054.8万阅读",
        "value": "|"
      },
      "platform": "微博",
      "crawlTime": "2025-01-18 01:45:24"
    },
    {
      "rank": "2025-01-17",
      "title": "陈奕迅现场收到一万颗爱心",
      "link": "https://s.weibo.com/weibo?q=%E9%99%88%E5%A5%95%E8%BF%85%E7%8E%B0%E5%9C%BA%E6%94%B6%E5%88%B0%E4%B8%80%E4%B8%87%E9%A2%97%E7%88%B1%E5%BF%83",
      "hot": {
        "category": "演出",
        "value": "36222"
      },
      "platform": "微博",
      "crawlTime": "2025-01-18 01:45:24"
    },
    {
      "rank": "2025-01-17",
      "title": "刘宇宁大战泥塑粉",
      "link": "https://s.weibo.com/weibo?q=%E5%88%98%E5%AE%87%E5%AE%81%E5%A4%A7%E6%88%98%E6%B3%A5%E5%A1%91%E7%B2%89",
      "hot": {
        "value": "6.7万"
      },
      "platform": "微博",
      "crawlTime": "2025-01-18 01:45:24"
    },
    {
      "rank": "2025-01-17",
      "title": "江苏队天塌了有13岁小孩姐扛着",
      "link": "https://s.weibo.com/weibo?q=%E6%B1%9F%E8%8B%8F%E9%98%9F%E5%A4%A9%E5%A1%8C%E4%BA%86%E6%9C%8913%E5%B2%81%E5%B0%8F%E5%AD%A9%E5%A7%90%E6%89%9B%E7%9D%80",
      "hot": {
        "category": "综艺",
        "value": "72203"
      },
      "platform": "微博",
      "crawlTime": "2025-01-18 01:45:24"
    },
    {
      "rank": "2025-01-17",
      "title": "大奉血屠三千里幕后大boss",
      "link": "https://s.weibo.com/weibo?q=%E5%A4%A7%E5%A5%89%E8%A1%80%E5%B1%A0%E4%B8%89%E5%8D%83%E9%87%8C%E5%B9%95%E5%90%8E%E5%A4%A7boss",
      "hot": {
        "category": "剧集",
        "value": "45690"
      },
      "platform": "微博",
      "crawlTime": "2025-01-18 01:45:24"
    },
    {
      "rank": "2025-01-17",
      "title": "斗笑社第三季定档",
      "link": "https://s.weibo.com/weibo?q=%E6%96%97%E7%AC%91%E7%A4%BE%E7%AC%AC%E4%B8%89%E5%AD%A3%E5%AE%9A%E6%A1%A3",
      "hot": {
        "category": "剧集",
        "value": "84340"
      },
      "platform": "微博",
      "crawlTime": "2025-01-18 01:45:24"
    },
    {
      "rank": "2025-01-17",
      "title": "刘宇宁入驻微博十周年",
      "link": "https://s.weibo.com/weibo?q=%E5%88%98%E5%AE%87%E5%AE%81%E5%85%A5%E9%A9%BB%E5%BE%AE%E5%8D%9A%E5%8D%81%E5%91%A8%E5%B9%B4",
      "hot": {
        "value": "10.2万"
      },
      "platform": "微博",
      "crawlTime": "2025-01-18 01:45:24"
    },
    {
      "rank": "2025-01-17",
      "title": "散装江苏在最强大脑具象化了",
      "link": "https://s.weibo.com/weibo?q=%E6%95%A3%E8%A3%85%E6%B1%9F%E8%8B%8F%E5%9C%A8%E6%9C%80%E5%BC%BA%E5%A4%A7%E8%84%91%E5%85%B7%E8%B1%A1%E5%8C%96%E4%BA%86",
      "hot": {
        "category": "综艺",
        "value": "67023"
      },
      "platform": "微博",
      "crawlTime": "2025-01-18 01:45:24"
    },
    {
      "rank": "2025-01-17",
      "title": "这座桥横竖都是世界第一",
      "link": "https://s.weibo.com/weibo?q=%E8%BF%99%E5%BA%A7%E6%A1%A5%E6%A8%AA%E7%AB%96%E9%83%BD%E6%98%AF%E4%B8%96%E7%95%8C%E7%AC%AC%E4%B8%80",
      "hot": {
        "category": "237.3万阅读",
        "value": "|"
      },
      "platform": "微博",
      "crawlTime": "2025-01-18 01:45:24"
    }
  ]
}